{
  "id": "P0190999",
  "subject": {
    "id": "P0190999",
    "alternateIds": [
      "FM3411"
    ],
    "vitalStatus": {
      "status": "ALIVE"
    },
    "sex": "FEMALE"
  },
  "phenotypicFeatures": [
    {
      "type": {
        "id": "HP:0100614",
        "label": "Myositis"
      }
    },
    {
      "type": {
        "id": "HP:0003805",
        "label": "Rimmed vacuoles"
      }
    },
    {
      "type": {
        "id": "HP:0003730",
        "label": "EMG: myotonic runs"
      }
    },
    {
      "type": {
        "id": "HP:0012103",
        "label": "Abnormality of the mitochondrion"
      }
    },
    {
      "type": {
        "id": "HP:0009071",
        "label": "Inflammatory myopathy"
      }
    }
  ],
  "interpretations": [
    {
      "id": "P0190999",
      "progressStatus": "UNSOLVED",
      "diagnosis": {
        "disease": {
          "id": "OMIM:147421",
          "label": "Inclusion Body Myositis"
        }
      }
    }
  ],
  "diseases": [
    {
      "term": {
        "id": "Orphanet:611",
        "label": "Inclusion body myositis"
      }
    },
    {
      "term": {
        "id": "OMIM:147421",
        "label": "Inclusion Body Myositis"
      }
    }
  ],
  "metaData": {
    "created": "2024-02-15T12:06:40Z",
    "createdBy": "rdconnect",
    "submittedBy": "uh-udd",
    "resources": [
      {
        "id": "hp",
        "name": "Human Phenotype Ontology",
        "url": "https://purl.obolibrary.org/obo/hp.owl",
        "version": "2020-12-07",
        "namespacePrefix": "HP",
        "iriPrefix": "https://purl.obolibrary.org/obo/HP_"
      },
      {
        "id": "orphanet",
        "name": "Orphanet Rare Disease Ontology",
        "url": "https://orpha.net/ontology/ORDO_en_3.1.owl",
        "version": "3.1",
        "namespacePrefix": "Orphanet",
        "iriPrefix": "https://www.orpha.net/ORDO/Orphanet_"
      },
      {
        "id": "hgnc",
        "name": "HUGO Gene Nomenclature Committee",
        "url": "https://www.genenames.org",
        "version": "2021-01-13",
        "namespacePrefix": "HGNC",
        "iriPrefix": "https://www.genenames.org/data/gene-symbol-report/#!/hgnc_id/"
      },
      {
        "id": "mim",
        "name": "Online Mendelian Inheritance in Man",
        "url": "https://omim.org/",
        "version": "2021-01-21",
        "namespacePrefix": "OMIM",
        "iriPrefix": "https://omim.org/entry/"
      }
    ],
    "phenopacketSchemaVersion": "2.0",
    "externalReferences": [
      {
        "id": "ERN-EURO-NMD"
      }
    ]
  }
}