{"id": "P0007848", "phenotypes": [{"type": {"id": "HP:0000276", "label": "Long face"}}, {"type": {"id": "HP:0000278", "label": "Retrognathia"}}, {"type": {"id": "HP:0000365", "label": "Hearing impairment"}}, {"type": {"id": "HP:0000545", "label": "Myopia"}}, {"type": {"id": "HP:0000729", "label": "Autistic behavior"}}, {"type": {"id": "HP:0000739", "label": "Anxiety"}}, {"type": {"id": "HP:0001310", "label": "Dysmetria"}}, {"type": {"id": "HP:0001608", "label": "Abnormality of the voice"}}, {"type": {"id": "HP:0002071", "label": "Abnormality of extrapyramidal motor function"}}, {"type": {"id": "HP:0002342", "label": "Intellectual disability, moderate"}}, {"type": {"id": "HP:0002705", "label": "High, narrow palate"}}, {"type": {"id": "HP:0011081", "label": "Incisor macrodontia"}}]}